degiro_api-0.1.dist-info/DESCRIPTION.rst
degiro_api-0.1.dist-info/METADATA
degiro_api-0.1.dist-info/RECORD
degiro_api-0.1.dist-info/WHEEL
degiro_api-0.1.dist-info/metadata.json
degiro_api-0.1.dist-info/top_level.txt
examples/__init__.py
examples/config.py
examples/search_products.py
src/__init__.py
src/client_info.py
src/constants.py
src/order.py
src/product.py
src/utils.py
test/__init__.py
