Metadata-Version: 2.0
Name: degiro-api
Version: 0.1
Summary: An unofficial DeGiro API wrapper for Python.
Home-page: https://github.com/FKatenbrink/DeGiro-API
Author: Florian Katenbrink
Author-email: f.katenbrink@gmail.com
License: MIT
Keywords: DeGiro API Wrapper
Platform: UNKNOWN
Classifier: Development Status :: 3 - Alpha
Classifier: License :: OSI Approved :: MIT License
Classifier: Programming Language :: Python :: 3.6
Classifier: Topic :: Internet :: WWW/HTTP
Requires-Dist: requests
